ludopy/__init__.py
ludopy/game.py
ludopy/glob.png
ludopy/player.py
ludopy/star.png
ludopy/visualizer.py
ludopy-1.5.0.dist-info/LICENSE
ludopy-1.5.0.dist-info/METADATA
ludopy-1.5.0.dist-info/WHEEL
ludopy-1.5.0.dist-info/top_level.txt
ludopy-1.5.0.dist-info/RECORD
