Metadata-Version: 2.1
Name: ludopy
Version: 1.5.0
Summary: A implementation of the LUDO game in python for use in AI or whatever you want
Home-page: https://github.com/SimonLBSoerensen/LUDOpy
Author: Simon L. B. Sørensen
Author-email: simonlyckbjaert@hotmail.com
License: MIT
Keywords: LUDO,game,AI
Classifier: Programming Language :: Python :: 3
Classifier: License :: OSI Approved :: MIT License
Classifier: Operating System :: OS Independent
Requires-Python: >=3.8
License-File: LICENSE
Requires-Dist: numpy
Requires-Dist: opencv-python (>=3.1)
